MANIFEST.in
README.md
setup.cfg
setup.py
aiocast/__init__.py
aiocast/_cast_server.py
aiocast/_cli.py
aiocast/_config.py
aiocast/_constants.py
aiocast/_version.py
aiocast/controls.html
aiocast.egg-info/PKG-INFO
aiocast.egg-info/SOURCES.txt
aiocast.egg-info/dependency_links.txt
aiocast.egg-info/entry_points.txt
aiocast.egg-info/requires.txt
aiocast.egg-info/top_level.txt