Metadata-Version: 2.1
Name: aiocast
Version: 0.0.3
Summary: Cast videos to chromecast from the commandline.
Home-page: https://github.com/T4rk1n/aiocast
Author: Philippe Duval
Author-email: t4rk@outlook.com
License: MIT
Keywords: cli,async,chromecast
Platform: UNKNOWN
Classifier: Programming Language :: Python
Classifier: Programming Language :: Python :: 3.6
Classifier: Programming Language :: Python :: 3.7
Classifier: License :: OSI Approved :: MIT License
